pydicom-stubs/__init__.pyi
pydicom-stubs/_dicom_dict.pyi
pydicom-stubs/_private_dict.pyi
pydicom-stubs/_type_definitions.pyi
pydicom-stubs/_uid_dict.pyi
pydicom-stubs/_version.pyi
pydicom-stubs/charset.pyi
pydicom-stubs/config.pyi
pydicom-stubs/datadict.pyi
pydicom-stubs/dataelem.pyi
pydicom-stubs/dataset.pyi
pydicom-stubs/dicomio.pyi
pydicom-stubs/encaps.pyi
pydicom-stubs/env_info.pyi
pydicom-stubs/errors.pyi
pydicom-stubs/filebase.pyi
pydicom-stubs/filereader.pyi
pydicom-stubs/fileset.pyi
pydicom-stubs/fileutil.pyi
pydicom-stubs/filewriter.pyi
pydicom-stubs/hooks.pyi
pydicom-stubs/jsonrep.pyi
pydicom-stubs/misc.pyi
pydicom-stubs/multival.pyi
pydicom-stubs/sequence.pyi
pydicom-stubs/tag.pyi
pydicom-stubs/uid.pyi
pydicom-stubs/valuerep.pyi
pydicom-stubs/values.pyi
pydicom-stubs/cli/__init__.pyi
pydicom-stubs/cli/codify.pyi
pydicom-stubs/cli/main.pyi
pydicom-stubs/cli/show.pyi
pydicom-stubs/data/__init__.pyi
pydicom-stubs/data/data_manager.pyi
pydicom-stubs/data/download.pyi
pydicom-stubs/data/retry.pyi
pydicom-stubs/encoders/__init__.pyi
pydicom-stubs/examples/__init__.pyi
pydicom-stubs/overlays/__init__.pyi
pydicom-stubs/overlays/numpy_handler.pyi
pydicom-stubs/pixel_data_handlers/__init__.pyi
pydicom-stubs/pixel_data_handlers/util.pyi
pydicom-stubs/pixels/__init__.pyi
pydicom-stubs/pixels/common.pyi
pydicom-stubs/pixels/processing.pyi
pydicom-stubs/pixels/utils.pyi
pydicom-stubs/pixels/decoders/__init__.pyi
pydicom-stubs/pixels/decoders/base.pyi
pydicom-stubs/pixels/encoders/__init__.pyi
pydicom-stubs/pixels/encoders/base.pyi
pydicom-stubs/sr/__init__.pyi
pydicom-stubs/sr/_cid_dict.pyi
pydicom-stubs/sr/_concepts_dict.pyi
pydicom-stubs/sr/_snomed_dict.pyi
pydicom-stubs/sr/codedict.pyi
pydicom-stubs/sr/coding.pyi
pydicom-stubs/util/__init__.pyi
pydicom-stubs/util/codify.pyi
pydicom-stubs/util/dump.pyi
pydicom-stubs/util/fixer.pyi
pydicom-stubs/util/hexutil.pyi
pydicom-stubs/util/leanread.pyi
pydicom-stubs/waveforms/__init__.pyi
types_pydicom-3.0.0.0.dist-info/LICENSE
types_pydicom-3.0.0.0.dist-info/METADATA
types_pydicom-3.0.0.0.dist-info/WHEEL
types_pydicom-3.0.0.0.dist-info/top_level.txt
types_pydicom-3.0.0.0.dist-info/RECORD
