Metadata-Version: 2.1
Name: types-pydicom
Version: 3.0.0.0
Summary: Extended type hints for pydicom
Author: pydicom contributors
License: MIT
Project-URL: homepage, https://github.com/pydicom/types-pydicom
Keywords: pydicom, typing
Classifier: License :: OSI Approved :: MIT License
Classifier: Programming Language :: Python
Classifier: Programming Language :: Python :: 3.10
Classifier: Programming Language :: Python :: 3.11
Classifier: Programming Language :: Python :: 3.12
Classifier: Typing :: Stubs Only
Requires-Python: >=3.10
License-File: LICENSE
Provides-Extra: dev
Requires-Dist: mypy ; extra == 'dev'
Requires-Dist: build ; extra == 'dev'
